docs/conf.py
scopes/__init__.py
scopes/merits.py
scopes/scheduler.py
scopes/scheduler_components.py
scopes_astro-0.4.0.dist-info/licenses/LICENSE.txt
tests/__init__.py
tests/conftest.py
tests/test_merit.py
tests/test_night.py
tests/test_observation.py
tests/test_overheads.py
tests/test_plan.py
tests/test_program.py
tests/test_target.py
scopes_astro-0.4.0.dist-info/METADATA
scopes_astro-0.4.0.dist-info/WHEEL
scopes_astro-0.4.0.dist-info/top_level.txt
scopes_astro-0.4.0.dist-info/RECORD
