Metadata-Version: 2.4
Name: scopes-astro
Version: 0.4.0
Summary: System for Coordinating Observational Planning and Efficient Scheduling
Author-email: Nicolas Unger <nicounger@proton.me>
License-Expression: GPL-3.0-only
Project-URL: GitHub, https://github.com/nicochunger/SCOPES
Project-URL: ReadTheDocs, https://scopes-docs.readthedocs.io/en/latest/
Project-URL: Documentation, https://github.com/nicochunger/SCOPES/blob/main/SCOPES_documentation.pdf
Project-URL: Changelog, https://scopes-docs.readthedocs.io/en/latest/changelog.html
Keywords: astronomy,scheduling,observation,planning
Classifier: Development Status :: 4 - Beta
Classifier: Intended Audience :: Science/Research
Classifier: Topic :: Scientific/Engineering :: Astronomy
Classifier: Programming Language :: Python :: 3
Classifier: Operating System :: OS Independent
Requires-Python: >=3.8
License-File: LICENSE.txt
Requires-Dist: numpy
Requires-Dist: pandas
Requires-Dist: matplotlib
Requires-Dist: astropy
Requires-Dist: astroplan
Requires-Dist: tqdm
Requires-Dist: pytz
Requires-Dist: timezonefinder
Provides-Extra: dev
Requires-Dist: pytest; extra == "dev"
Requires-Dist: sphinx; extra == "dev"
Dynamic: license-file
